_pyinstaller_hooks_contrib/__init__.py
_pyinstaller_hooks_contrib/compat.py
_pyinstaller_hooks_contrib/rthooks.dat
_pyinstaller_hooks_contrib/__pycache__/__init__.cpython-39.pyc
_pyinstaller_hooks_contrib/pre_find_module_path/__init__.py
_pyinstaller_hooks_contrib/pre_safe_import_module/__init__.py
_pyinstaller_hooks_contrib/pre_safe_import_module/hook-tensorflow.py
_pyinstaller_hooks_contrib/pre_safe_import_module/hook-win32com.py
_pyinstaller_hooks_contrib/rthooks/__init__.py
_pyinstaller_hooks_contrib/rthooks/pyi_rth_cryptography_openssl.py
_pyinstaller_hooks_contrib/rthooks/pyi_rth_enchant.py
_pyinstaller_hooks_contrib/rthooks/pyi_rth_ffpyplayer.py
_pyinstaller_hooks_contrib/rthooks/pyi_rth_findlibs.py
_pyinstaller_hooks_contrib/rthooks/pyi_rth_nltk.py
_pyinstaller_hooks_contrib/rthooks/pyi_rth_osgeo.py
_pyinstaller_hooks_contrib/rthooks/pyi_rth_pygraphviz.py
_pyinstaller_hooks_contrib/rthooks/pyi_rth_pyproj.py
_pyinstaller_hooks_contrib/rthooks/pyi_rth_pyqtgraph_multiprocess.py
_pyinstaller_hooks_contrib/rthooks/pyi_rth_pythoncom.py
_pyinstaller_hooks_contrib/rthooks/pyi_rth_pywintypes.py
_pyinstaller_hooks_contrib/rthooks/pyi_rth_tensorflow.py
_pyinstaller_hooks_contrib/rthooks/pyi_rth_traitlets.py
_pyinstaller_hooks_contrib/rthooks/pyi_rth_usb.py
_pyinstaller_hooks_contrib/stdhooks/__init__.py
_pyinstaller_hooks_contrib/stdhooks/hook-BTrees.py
_pyinstaller_hooks_contrib/stdhooks/hook-CTkMessagebox.py
_pyinstaller_hooks_contrib/stdhooks/hook-Crypto.py
_pyinstaller_hooks_contrib/stdhooks/hook-Cryptodome.py
_pyinstaller_hooks_contrib/stdhooks/hook-HtmlTestRunner.py
_pyinstaller_hooks_contrib/stdhooks/hook-IPython.py
_pyinstaller_hooks_contrib/stdhooks/hook-OpenGL.py
_pyinstaller_hooks_contrib/stdhooks/hook-OpenGL_accelerate.py
_pyinstaller_hooks_contrib/stdhooks/hook-PyTaskbar.py
_pyinstaller_hooks_contrib/stdhooks/hook-Xlib.py
_pyinstaller_hooks_contrib/stdhooks/hook-_mssql.py
_pyinstaller_hooks_contrib/stdhooks/hook-_mysql.py
pyinstaller_hooks_contrib-2024.10.dist-info/LICENSE
pyinstaller_hooks_contrib-2024.10.dist-info/METADATA
pyinstaller_hooks_contrib-2024.10.dist-info/WHEEL
pyinstaller_hooks_contrib-2024.10.dist-info/entry_points.txt
pyinstaller_hooks_contrib-2024.10.dist-info/top_level.txt
pyinstaller_hooks_contrib-2024.10.dist-info/RECORD
