Metadata-Version: 2.1
Name: pyinstaller-hooks-contrib
Version: 2024.10
Summary: Community maintained hooks for PyInstaller
Home-page: https://github.com/pyinstaller/pyinstaller-hooks-contrib
Download-URL: https://pypi.org/project/pyinstaller-hooks-contrib
Maintainer: Legorooj
Maintainer-email: legorooj@protonmail.com
Keywords: pyinstaller development hooks
Classifier: Intended Audience :: Developers
Classifier: Topic :: Software Development :: Build Tools
Classifier: License :: OSI Approved :: Apache Software License
Classifier: License :: OSI Approved :: GNU General Public License v2 (GPLv2)
Classifier: Natural Language :: English
Classifier: Operating System :: OS Independent
Classifier: Programming Language :: Python
Classifier: Programming Language :: Python :: 3
Requires-Python: >=3.8
License-File: LICENSE
Requires-Dist: setuptools>=42.0.0
Requires-Dist: importlib_metadata>=4.6; python_version < "3.10"
Requires-Dist: packaging>=22.0
